{
  "$schema": "https://ui.shadcn.com/schema/registry-item.json",
  "name": "voyant-markets-market-dialog",
  "title": "Market Dialog",
  "description": "Create/edit dialog for market records wired to markets-react mutations.",
  "dependencies": ["@voyantjs/markets-react", "lucide-react"],
  "registryDependencies": ["dialog", "input", "label", "select"],
  "files": [
    {
      "path": "registry/markets/market-dialog.tsx",
      "content": "export {\n  MarketDialog,\n  type MarketDialogProps,\n} from \"../../../markets-ui/src/components/market-dialog\"\n",
      "type": "registry:component",
      "target": "components/voyant/markets/market-dialog.tsx"
    }
  ],
  "type": "registry:component"
}
