{
  "version": "7",
  "dialect": "postgresql",
  "entries": [
    {
      "idx": 0,
      "version": "7",
      "when": 1781683434217,
      "tag": "0000_framework_baseline",
      "breakpoints": true
    },
    {
      "idx": 1,
      "version": "7",
      "when": 1781697751693,
      "tag": "0001_framework_baseline",
      "breakpoints": true
    },
    {
      "idx": 2,
      "version": "7",
      "when": 1781711913836,
      "tag": "0002_framework_baseline",
      "breakpoints": true
    },
    {
      "idx": 3,
      "version": "7",
      "when": 1781712605226,
      "tag": "0003_framework_baseline",
      "breakpoints": true
    },
    {
      "idx": 4,
      "version": "7",
      "when": 1781715425179,
      "tag": "0004_framework_baseline",
      "breakpoints": true
    },
    {
      "idx": 5,
      "version": "7",
      "when": 1781823278682,
      "tag": "0005_person_directory_view",
      "breakpoints": true
    },
    {
      "idx": 6,
      "version": "7",
      "when": 1781826105822,
      "tag": "0006_framework_baseline",
      "breakpoints": true
    },
    {
      "idx": 7,
      "version": "7",
      "when": 1781827263947,
      "tag": "0007_framework_baseline",
      "breakpoints": true
    },
    {
      "idx": 8,
      "version": "7",
      "when": 1781830944766,
      "tag": "0008_framework_baseline",
      "breakpoints": true
    },
    {
      "idx": 9,
      "version": "7",
      "when": 1781831361441,
      "tag": "0009_framework_baseline",
      "breakpoints": true
    }
  ]
}