{
  "openapi": "3.1.0",
  "info": {
    "title": "Voyant Framework API",
    "version": "0.0.0",
    "description": "Generated from the Voyant framework's standard module composition. Do not edit by hand."
  },
  "servers": [
    {
      "url": "/",
      "description": "This deployment (same origin)"
    }
  ],
  "components": {
    "schemas": {
      "CatalogSearchFilter": {
        "anyOf": [
          {
            "type": "object",
            "properties": {
              "kind": {
                "type": "string",
                "enum": [
                  "eq"
                ]
              },
              "field": {
                "type": "string",
                "minLength": 1
              },
              "value": {
                "anyOf": [
                  {
                    "type": "string"
                  },
                  {
                    "type": "number"
                  },
                  {
                    "type": "boolean"
                  }
                ]
              }
            },
            "required": [
              "kind",
              "field",
              "value"
            ]
          },
          {
            "type": "object",
            "properties": {
              "kind": {
                "type": "string",
                "enum": [
                  "in"
                ]
              },
              "field": {
                "type": "string",
                "minLength": 1
              },
              "values": {
                "type": "array",
                "items": {
                  "anyOf": [
                    {
                      "type": "string"
                    },
                    {
                      "type": "number"
                    }
                  ]
                }
              }
            },
            "required": [
              "kind",
              "field",
              "values"
            ]
          },
          {
            "type": "object",
            "properties": {
              "kind": {
                "type": "string",
                "enum": [
                  "range"
                ]
              },
              "field": {
                "type": "string",
                "minLength": 1
              },
              "gte": {
                "type": "number"
              },
              "lte": {
                "type": "number"
              }
            },
            "required": [
              "kind",
              "field"
            ]
          },
          {
            "type": "object",
            "properties": {
              "kind": {
                "type": "string",
                "enum": [
                  "and"
                ]
              },
              "clauses": {
                "type": "array",
                "items": {
                  "$ref": "#/components/schemas/CatalogSearchFilter"
                }
              }
            },
            "required": [
              "kind",
              "clauses"
            ]
          },
          {
            "type": "object",
            "properties": {
              "kind": {
                "type": "string",
                "enum": [
                  "or"
                ]
              },
              "clauses": {
                "type": "array",
                "items": {
                  "$ref": "#/components/schemas/CatalogSearchFilter"
                }
              }
            },
            "required": [
              "kind",
              "clauses"
            ]
          }
        ]
      },
      "BookingProductDetailsInput": {
        "type": "object",
        "properties": {
          "productId": {
            "type": [
              "string",
              "null"
            ]
          },
          "optionId": {
            "type": [
              "string",
              "null"
            ]
          }
        }
      },
      "BookingItemProductDetailsInput": {
        "type": "object",
        "properties": {
          "productId": {
            "type": [
              "string",
              "null"
            ]
          },
          "optionId": {
            "type": [
              "string",
              "null"
            ]
          },
          "unitId": {
            "type": [
              "string",
              "null"
            ]
          },
          "supplierServiceId": {
            "type": [
              "string",
              "null"
            ]
          }
        }
      }
    },
    "parameters": {}
  },
  "paths": {
    "/v1/admin/team/members": {
      "get": {
        "operationId": "listTeamMembers",
        "x-voyant-api-id": "@voyant-travel/auth#team.api.admin",
        "responses": {
          "200": {
            "description": "HTTP 200"
          },
          "401": {
            "description": "HTTP 401"
          },
          "403": {
            "description": "HTTP 403"
          },
          "404": {
            "description": "HTTP 404"
          },
          "501": {
            "description": "HTTP 501"
          }
        },
        "summary": "GET /v1/admin/team/members",
        "tags": [
          "team"
        ],
        "x-voyant-module": "team",
        "x-voyant-surface": "admin"
      }
    },
    "/v1/admin/team/roles": {
      "get": {
        "operationId": "listTeamRoles",
        "x-voyant-api-id": "@voyant-travel/auth#team.api.admin",
        "responses": {
          "200": {
            "description": "HTTP 200"
          },
          "401": {
            "description": "HTTP 401"
          },
          "403": {
            "description": "HTTP 403"
          },
          "404": {
            "description": "HTTP 404"
          },
          "501": {
            "description": "HTTP 501"
          }
        },
        "summary": "GET /v1/admin/team/roles",
        "tags": [
          "team"
        ],
        "x-voyant-module": "team",
        "x-voyant-surface": "admin"
      }
    },
    "/v1/admin/team/invitations": {
      "get": {
        "operationId": "listTeamInvitations",
        "x-voyant-api-id": "@voyant-travel/auth#team.api.admin",
        "responses": {
          "200": {
            "description": "HTTP 200"
          },
          "401": {
            "description": "HTTP 401"
          },
          "403": {
            "description": "HTTP 403"
          },
          "404": {
            "description": "HTTP 404"
          },
          "501": {
            "description": "HTTP 501"
          }
        },
        "summary": "GET /v1/admin/team/invitations",
        "tags": [
          "team"
        ],
        "x-voyant-module": "team",
        "x-voyant-surface": "admin"
      },
      "post": {
        "operationId": "createTeamInvitation",
        "x-voyant-api-id": "@voyant-travel/auth#team.api.admin",
        "requestBody": {
          "required": true,
          "content": {
            "application/json": {
              "schema": {
                "type": "object",
                "properties": {
                  "email": {
                    "type": "string",
                    "format": "email"
                  },
                  "roleSlug": {
                    "type": [
                      "string",
                      "null"
                    ],
                    "minLength": 1,
                    "maxLength": 120
                  },
                  "expiresInDays": {
                    "type": "integer",
                    "minimum": 1,
                    "maximum": 30
                  }
                },
                "required": [
                  "email"
                ]
              }
            }
          }
        },
        "responses": {
          "201": {
            "description": "HTTP 201"
          },
          "400": {
            "description": "HTTP 400"
          },
          "401": {
            "description": "HTTP 401"
          },
          "403": {
            "description": "HTTP 403"
          },
          "404": {
            "description": "HTTP 404"
          },
          "501": {
            "description": "HTTP 501"
          }
        },
        "summary": "POST /v1/admin/team/invitations",
        "tags": [
          "team"
        ],
        "x-voyant-module": "team",
        "x-voyant-surface": "admin"
      }
    },
    "/v1/admin/team/invitations/{invitationId}": {
      "delete": {
        "operationId": "revokeTeamInvitation",
        "x-voyant-api-id": "@voyant-travel/auth#team.api.admin",
        "parameters": [
          {
            "schema": {
              "type": "string"
            },
            "required": true,
            "name": "invitationId",
            "in": "path"
          }
        ],
        "responses": {
          "204": {
            "description": "HTTP 204"
          },
          "401": {
            "description": "HTTP 401"
          },
          "403": {
            "description": "HTTP 403"
          },
          "404": {
            "description": "HTTP 404"
          },
          "501": {
            "description": "HTTP 501"
          }
        },
        "summary": "DELETE /v1/admin/team/invitations/{invitationId}",
        "tags": [
          "team"
        ],
        "x-voyant-module": "team",
        "x-voyant-surface": "admin"
      }
    },
    "/v1/admin/team/members/{membershipId}/access": {
      "put": {
        "operationId": "setTeamMemberAccess",
        "x-voyant-api-id": "@voyant-travel/auth#team.api.admin",
        "parameters": [
          {
            "schema": {
              "type": "string"
            },
            "required": true,
            "name": "membershipId",
            "in": "path"
          }
        ],
        "requestBody": {
          "required": true,
          "content": {
            "application/json": {
              "schema": {
                "type": "object",
                "properties": {
                  "hasAccess": {
                    "type": "boolean"
                  }
                },
                "required": [
                  "hasAccess"
                ]
              }
            }
          }
        },
        "responses": {
          "200": {
            "description": "HTTP 200"
          },
          "400": {
            "description": "HTTP 400"
          },
          "401": {
            "description": "HTTP 401"
          },
          "403": {
            "description": "HTTP 403"
          },
          "404": {
            "description": "HTTP 404"
          },
          "501": {
            "description": "HTTP 501"
          }
        },
        "summary": "PUT /v1/admin/team/members/{membershipId}/access",
        "tags": [
          "team"
        ],
        "x-voyant-module": "team",
        "x-voyant-surface": "admin"
      }
    },
    "/v1/admin/team/members/{membershipId}/permissions": {
      "put": {
        "operationId": "setTeamMemberPermissions",
        "x-voyant-api-id": "@voyant-travel/auth#team.api.admin",
        "parameters": [
          {
            "schema": {
              "type": "string"
            },
            "required": true,
            "name": "membershipId",
            "in": "path"
          }
        ],
        "requestBody": {
          "required": true,
          "content": {
            "application/json": {
              "schema": {
                "type": "object",
                "properties": {
                  "permissions": {
                    "type": "array",
                    "items": {
                      "type": "string",
                      "minLength": 1,
                      "maxLength": 120
                    },
                    "maxItems": 200
                  }
                },
                "required": [
                  "permissions"
                ]
              }
            }
          }
        },
        "responses": {
          "200": {
            "description": "HTTP 200"
          },
          "400": {
            "description": "HTTP 400"
          },
          "401": {
            "description": "HTTP 401"
          },
          "403": {
            "description": "HTTP 403"
          },
          "404": {
            "description": "HTTP 404"
          },
          "501": {
            "description": "HTTP 501"
          }
        },
        "summary": "PUT /v1/admin/team/members/{membershipId}/permissions",
        "tags": [
          "team"
        ],
        "x-voyant-module": "team",
        "x-voyant-surface": "admin"
      }
    }
  },
  "webhooks": {}
}
