{
  "$schema": "https://ui.shadcn.com/schema/registry-item.json",
  "name": "voyant-pricing-option-unit-price-rules-page",
  "title": "Option Unit Price Rules Page",
  "description": "Server-paginated CRUD table for per-unit option pricing rules with hydrated option rule and pricing category labels.",
  "dependencies": ["lucide-react", "@voyantjs/pricing-react", "@voyantjs/products-react"],
  "registryDependencies": [
    "badge",
    "button",
    "table",
    "voyant-pricing-option-unit-price-rule-dialog"
  ],
  "files": [
    {
      "path": "registry/pricing/option-unit-price-rules-page.tsx",
      "content": "\"use client\"\n\nimport type { ColumnDef } from \"@tanstack/react-table\"\nimport {\n  type OptionUnitPriceRuleRecord,\n  useOptionUnitPriceRuleMutation,\n  useOptionUnitPriceRules,\n} from \"@voyantjs/pricing-react\"\nimport { usePricingUiI18nOrDefault, usePricingUiMessagesOrDefault } from \"@voyantjs/pricing-ui\"\nimport { Pencil, Plus, Trash2 } from \"lucide-react\"\nimport * as React from \"react\"\n\nimport { Badge, Button } from \"@/components/ui\"\nimport { DataTable } from \"@/components/ui/data-table\"\n\nimport { useRegistryPricingMessagesOrDefault } from \"./i18n\"\nimport { OptionUnitPriceRuleDialog } from \"./option-unit-price-rule-dialog\"\nimport { OptionPriceRuleLabel, PricingCategoryLabel } from \"./pricing-shared-labels\"\n\nconst PAGE_SIZE = 25\n\nexport function OptionUnitPriceRulesPage() {\n  const sharedI18n = usePricingUiI18nOrDefault()\n  const sharedMessages = usePricingUiMessagesOrDefault()\n  const registryMessages = useRegistryPricingMessagesOrDefault()\n  const pageMessages = registryMessages.optionUnitPriceRulesPage\n  const [dialogOpen, setDialogOpen] = React.useState(false)\n  const [editing, setEditing] = React.useState<OptionUnitPriceRuleRecord | undefined>()\n  const [pageIndex, setPageIndex] = React.useState(0)\n\n  const { data, isPending, refetch } = useOptionUnitPriceRules({\n    limit: PAGE_SIZE,\n    offset: pageIndex * PAGE_SIZE,\n  })\n  const { remove } = useOptionUnitPriceRuleMutation()\n\n  const columns = React.useMemo<ColumnDef<OptionUnitPriceRuleRecord>[]>(\n    () => [\n      {\n        accessorKey: \"optionPriceRuleId\",\n        header: pageMessages.columns.optionPriceRule,\n        cell: ({ row }) => <OptionPriceRuleLabel id={row.original.optionPriceRuleId} />,\n      },\n      {\n        accessorKey: \"unitId\",\n        header: pageMessages.columns.unit,\n        cell: ({ row }) => <span className=\"font-mono text-xs\">{row.original.unitId}</span>,\n      },\n      {\n        accessorKey: \"pricingCategoryId\",\n        header: pageMessages.columns.pricingCategory,\n        cell: ({ row }) =>\n          row.original.pricingCategoryId ? (\n            <PricingCategoryLabel id={row.original.pricingCategoryId} />\n          ) : (\n            \"—\"\n          ),\n      },\n      {\n        accessorKey: \"pricingMode\",\n        header: pageMessages.columns.mode,\n        cell: ({ row }) => (\n          <Badge variant=\"outline\" className=\"capitalize\">\n            {sharedMessages.common.unitPricingModeLabels[row.original.pricingMode]}\n          </Badge>\n        ),\n      },\n      {\n        accessorKey: \"sellAmountCents\",\n        header: pageMessages.columns.sell,\n        cell: ({ row }) => (\n          <span className=\"font-mono text-xs\">\n            {row.original.sellAmountCents != null\n              ? sharedI18n.formatNumber(row.original.sellAmountCents / 100, {\n                  minimumFractionDigits: 2,\n                  maximumFractionDigits: 2,\n                })\n              : \"-\"}\n          </span>\n        ),\n      },\n      {\n        accessorKey: \"costAmountCents\",\n        header: pageMessages.columns.cost,\n        cell: ({ row }) => (\n          <span className=\"font-mono text-xs\">\n            {row.original.costAmountCents != null\n              ? sharedI18n.formatNumber(row.original.costAmountCents / 100, {\n                  minimumFractionDigits: 2,\n                  maximumFractionDigits: 2,\n                })\n              : \"-\"}\n          </span>\n        ),\n      },\n      {\n        accessorKey: \"quantity\",\n        header: pageMessages.columns.quantity,\n        cell: ({ row }) => (\n          <span className=\"font-mono text-xs text-muted-foreground\">\n            {row.original.minQuantity ?? 0}-{row.original.maxQuantity ?? \"∞\"}\n          </span>\n        ),\n      },\n      {\n        accessorKey: \"active\",\n        header: pageMessages.columns.status,\n        cell: ({ row }) => (\n          <Badge variant={row.original.active ? \"default\" : \"outline\"}>\n            {row.original.active ? sharedMessages.common.active : sharedMessages.common.inactive}\n          </Badge>\n        ),\n      },\n      {\n        id: \"actions\",\n        header: () => <div className=\"w-20\" />,\n        cell: ({ row }) => (\n          <div className=\"flex items-center justify-end gap-1\">\n            <button\n              type=\"button\"\n              onClick={() => {\n                setEditing(row.original)\n                setDialogOpen(true)\n              }}\n              className=\"text-muted-foreground hover:text-foreground\"\n            >\n              <Pencil className=\"h-3.5 w-3.5\" />\n            </button>\n            <button\n              type=\"button\"\n              onClick={() => {\n                if (confirm(pageMessages.labels.deleteConfirm)) {\n                  remove.mutate(row.original.id, { onSuccess: () => void refetch() })\n                }\n              }}\n              className=\"text-muted-foreground hover:text-destructive\"\n            >\n              <Trash2 className=\"h-3.5 w-3.5\" />\n            </button>\n          </div>\n        ),\n      },\n    ],\n    [pageMessages, refetch, remove, sharedI18n, sharedMessages],\n  )\n\n  return (\n    <div className=\"flex flex-col gap-6\">\n      <div className=\"flex items-start justify-between gap-4\">\n        <div>\n          <h2 className=\"text-lg font-semibold tracking-tight\">{pageMessages.title}</h2>\n          <p className=\"text-sm text-muted-foreground\">{pageMessages.description}</p>\n        </div>\n        <Button\n          onClick={() => {\n            setEditing(undefined)\n            setDialogOpen(true)\n          }}\n        >\n          <Plus className=\"mr-2 h-4 w-4\" />\n          {pageMessages.add}\n        </Button>\n      </div>\n\n      <DataTable\n        columns={columns}\n        data={data?.data ?? []}\n        emptyMessage={isPending ? pageMessages.emptyLoading : pageMessages.empty}\n        pagination={{\n          pageIndex,\n          pageSize: PAGE_SIZE,\n          total: data?.total ?? 0,\n          onPageIndexChange: setPageIndex,\n        }}\n      />\n\n      <OptionUnitPriceRuleDialog\n        open={dialogOpen}\n        onOpenChange={setDialogOpen}\n        rule={editing}\n        onSuccess={() => {\n          setDialogOpen(false)\n          setEditing(undefined)\n          void refetch()\n        }}\n      />\n    </div>\n  )\n}\n",
      "type": "registry:component",
      "target": "components/voyant/pricing/option-unit-price-rules-page.tsx"
    }
  ],
  "type": "registry:component"
}
