{
  "$schema": "https://ui.shadcn.com/schema/registry-item.json",
  "name": "voyant-suppliers-page",
  "title": "Suppliers Page",
  "description": "Searchable suppliers management page shell with data table and create action.",
  "dependencies": ["lucide-react", "@voyantjs/suppliers-react"],
  "registryDependencies": ["badge", "button", "input", "table"],
  "files": [
    {
      "path": "registry/suppliers/suppliers-page.tsx",
      "content": "export { SuppliersPage } from \"../../../suppliers-ui/src/components/suppliers-page\"\n",
      "type": "registry:component",
      "target": "components/voyant/suppliers/suppliers-page.tsx"
    }
  ],
  "type": "registry:component"
}
