{
  "id": "cb960681-91f3-45ac-a4a9-a4c77e6b7d3b",
  "prevId": "00000000-0000-0000-0000-000000000000",
  "version": "7",
  "dialect": "postgresql",
  "tables": {
    "public.workflow_run_steps": {
      "name": "workflow_run_steps",
      "schema": "",
      "columns": {
        "id": {
          "name": "id",
          "type": "text",
          "primaryKey": true,
          "notNull": true
        },
        "run_id": {
          "name": "run_id",
          "type": "text",
          "primaryKey": false,
          "notNull": true
        },
        "step_name": {
          "name": "step_name",
          "type": "text",
          "primaryKey": false,
          "notNull": true
        },
        "sequence": {
          "name": "sequence",
          "type": "integer",
          "primaryKey": false,
          "notNull": true
        },
        "status": {
          "name": "status",
          "type": "workflow_run_step_status",
          "typeSchema": "public",
          "primaryKey": false,
          "notNull": true,
          "default": "'running'"
        },
        "output": {
          "name": "output",
          "type": "jsonb",
          "primaryKey": false,
          "notNull": false
        },
        "error": {
          "name": "error",
          "type": "jsonb",
          "primaryKey": false,
          "notNull": false
        },
        "started_at": {
          "name": "started_at",
          "type": "timestamp with time zone",
          "primaryKey": false,
          "notNull": true,
          "default": "now()"
        },
        "completed_at": {
          "name": "completed_at",
          "type": "timestamp with time zone",
          "primaryKey": false,
          "notNull": false
        },
        "duration_ms": {
          "name": "duration_ms",
          "type": "integer",
          "primaryKey": false,
          "notNull": false
        }
      },
      "indexes": {
        "idx_workflow_run_steps_run": {
          "name": "idx_workflow_run_steps_run",
          "columns": [
            {
              "expression": "run_id",
              "isExpression": false,
              "asc": true,
              "nulls": "last"
            },
            {
              "expression": "sequence",
              "isExpression": false,
              "asc": true,
              "nulls": "last"
            }
          ],
          "isUnique": false,
          "concurrently": false,
          "method": "btree",
          "with": {}
        },
        "idx_workflow_run_steps_status": {
          "name": "idx_workflow_run_steps_status",
          "columns": [
            {
              "expression": "status",
              "isExpression": false,
              "asc": true,
              "nulls": "last"
            }
          ],
          "isUnique": false,
          "concurrently": false,
          "method": "btree",
          "with": {}
        }
      },
      "foreignKeys": {
        "workflow_run_steps_run_id_workflow_runs_id_fk": {
          "name": "workflow_run_steps_run_id_workflow_runs_id_fk",
          "tableFrom": "workflow_run_steps",
          "tableTo": "workflow_runs",
          "columnsFrom": [
            "run_id"
          ],
          "columnsTo": [
            "id"
          ],
          "onDelete": "cascade",
          "onUpdate": "no action"
        }
      },
      "compositePrimaryKeys": {},
      "uniqueConstraints": {},
      "policies": {},
      "checkConstraints": {},
      "isRLSEnabled": false
    },
    "public.workflow_runs": {
      "name": "workflow_runs",
      "schema": "",
      "columns": {
        "id": {
          "name": "id",
          "type": "text",
          "primaryKey": true,
          "notNull": true
        },
        "workflow_name": {
          "name": "workflow_name",
          "type": "text",
          "primaryKey": false,
          "notNull": true
        },
        "trigger": {
          "name": "trigger",
          "type": "text",
          "primaryKey": false,
          "notNull": true,
          "default": "'manual'"
        },
        "correlation_id": {
          "name": "correlation_id",
          "type": "text",
          "primaryKey": false,
          "notNull": false
        },
        "tags": {
          "name": "tags",
          "type": "jsonb",
          "primaryKey": false,
          "notNull": true,
          "default": "'[]'::jsonb"
        },
        "status": {
          "name": "status",
          "type": "workflow_run_status",
          "typeSchema": "public",
          "primaryKey": false,
          "notNull": true,
          "default": "'running'"
        },
        "input": {
          "name": "input",
          "type": "jsonb",
          "primaryKey": false,
          "notNull": false
        },
        "result": {
          "name": "result",
          "type": "jsonb",
          "primaryKey": false,
          "notNull": false
        },
        "error": {
          "name": "error",
          "type": "jsonb",
          "primaryKey": false,
          "notNull": false
        },
        "parent_run_id": {
          "name": "parent_run_id",
          "type": "text",
          "primaryKey": false,
          "notNull": false
        },
        "triggered_by_user_id": {
          "name": "triggered_by_user_id",
          "type": "text",
          "primaryKey": false,
          "notNull": false
        },
        "resume_from_step": {
          "name": "resume_from_step",
          "type": "text",
          "primaryKey": false,
          "notNull": false
        },
        "started_at": {
          "name": "started_at",
          "type": "timestamp with time zone",
          "primaryKey": false,
          "notNull": true,
          "default": "now()"
        },
        "completed_at": {
          "name": "completed_at",
          "type": "timestamp with time zone",
          "primaryKey": false,
          "notNull": false
        },
        "duration_ms": {
          "name": "duration_ms",
          "type": "integer",
          "primaryKey": false,
          "notNull": false
        },
        "created_at": {
          "name": "created_at",
          "type": "timestamp with time zone",
          "primaryKey": false,
          "notNull": true,
          "default": "now()"
        },
        "updated_at": {
          "name": "updated_at",
          "type": "timestamp with time zone",
          "primaryKey": false,
          "notNull": true,
          "default": "now()"
        }
      },
      "indexes": {
        "idx_workflow_runs_workflow": {
          "name": "idx_workflow_runs_workflow",
          "columns": [
            {
              "expression": "workflow_name",
              "isExpression": false,
              "asc": true,
              "nulls": "last"
            },
            {
              "expression": "started_at",
              "isExpression": false,
              "asc": true,
              "nulls": "last"
            }
          ],
          "isUnique": false,
          "concurrently": false,
          "method": "btree",
          "with": {}
        },
        "idx_workflow_runs_status_started": {
          "name": "idx_workflow_runs_status_started",
          "columns": [
            {
              "expression": "status",
              "isExpression": false,
              "asc": true,
              "nulls": "last"
            },
            {
              "expression": "started_at",
              "isExpression": false,
              "asc": true,
              "nulls": "last"
            }
          ],
          "isUnique": false,
          "concurrently": false,
          "method": "btree",
          "with": {}
        },
        "idx_workflow_runs_correlation": {
          "name": "idx_workflow_runs_correlation",
          "columns": [
            {
              "expression": "correlation_id",
              "isExpression": false,
              "asc": true,
              "nulls": "last"
            }
          ],
          "isUnique": false,
          "concurrently": false,
          "method": "btree",
          "with": {}
        },
        "idx_workflow_runs_parent": {
          "name": "idx_workflow_runs_parent",
          "columns": [
            {
              "expression": "parent_run_id",
              "isExpression": false,
              "asc": true,
              "nulls": "last"
            }
          ],
          "isUnique": false,
          "concurrently": false,
          "method": "btree",
          "with": {}
        },
        "idx_workflow_runs_tags_gin": {
          "name": "idx_workflow_runs_tags_gin",
          "columns": [
            {
              "expression": "\"tags\"",
              "asc": true,
              "isExpression": true,
              "nulls": "last"
            }
          ],
          "isUnique": false,
          "concurrently": false,
          "method": "gin",
          "with": {}
        }
      },
      "foreignKeys": {},
      "compositePrimaryKeys": {},
      "uniqueConstraints": {},
      "policies": {},
      "checkConstraints": {
        "ck_workflow_runs_completion": {
          "name": "ck_workflow_runs_completion",
          "value": "(\n        \"workflow_runs\".\"status\" = 'running' AND \"workflow_runs\".\"completed_at\" IS NULL\n      ) OR (\n        \"workflow_runs\".\"status\" <> 'running' AND \"workflow_runs\".\"completed_at\" IS NOT NULL\n      )"
        }
      },
      "isRLSEnabled": false
    }
  },
  "enums": {
    "public.workflow_run_status": {
      "name": "workflow_run_status",
      "schema": "public",
      "values": [
        "running",
        "succeeded",
        "failed",
        "cancelled"
      ]
    },
    "public.workflow_run_step_status": {
      "name": "workflow_run_step_status",
      "schema": "public",
      "values": [
        "running",
        "succeeded",
        "failed",
        "skipped",
        "compensated"
      ]
    }
  },
  "schemas": {},
  "sequences": {},
  "roles": {},
  "policies": {},
  "views": {},
  "_meta": {
    "columns": {},
    "schemas": {},
    "tables": {}
  }
}